{
  "repo": {
    "repo": "jvvinoth/mongpt-marketing",
    "description": "MonGPT is the marketing site for an AI chat + voice customer support agent targeting Asian markets with multi-language support (Hindi, Tamil, Chinese, Malay, Japanese, Thai, and more). The site is a static Next.js export on Cloudflare Pages, featuring locale-aware landing pages, a docs hub, a pricing page, and 26+ free SEO tools that drive lead generation via a footer link mesh.",
    "framework": "Next.js 16 (static export) · TypeScript · Tailwind CSS v4 · Cloudflare Pages",
    "fileCount": 129,
    "keyAreas": [
      "i18n geo-locale routing",
      "SEO tool mesh (26+ free tools)",
      "demo widget API integration",
      "docs hub",
      "hreflang sitemap"
    ]
  },
  "cards": [
    {
      "track": "level_up",
      "title": "Add SSRF guards and size limits to demo endpoints",
      "rationale": "Scrape and parse-file endpoints accept arbitrary URLs and files with zero validation client-side.",
      "bullets": [
        "Validate URL scheme/host in ChatWithSource loadUrl",
        "Enforce max file size in ConverterTool onFile",
        "Add client-side rate limiting to all /api/demo calls"
      ],
      "category": "security",
      "impact": "high",
      "effort": "M",
      "risk": "low",
      "targetFiles": [
        "src/components/ChatWithSource.tsx",
        "src/components/ConverterTool.tsx",
        "src/components/GeneratorTool.tsx"
      ],
      "id": "card-1",
      "status": "proposed"
    },
    {
      "track": "level_up",
      "title": "Add unit tests for markdown converters and i18n utils",
      "rationale": "Core conversion logic in toMarkdown.ts and locale routing have zero test coverage.",
      "bullets": [
        "Test csvToMarkdown and jsonToMarkdown edge cases",
        "Test alternatesFor and localeHref output",
        "Add vitest config — jsdom already in devDeps"
      ],
      "category": "tests",
      "impact": "medium",
      "effort": "S",
      "risk": "low",
      "targetFiles": [
        "src/lib/toMarkdown.ts",
        "src/lib/i18n.ts",
        "src/lib/urls.ts",
        "package.json"
      ],
      "id": "card-2",
      "status": "proposed"
    },
    {
      "track": "level_up",
      "title": "Add mobile navigation menu to header",
      "rationale": "Nav links are hidden on mobile with no hamburger fallback, losing conversion paths.",
      "bullets": [
        "Add hamburger toggle button visible below md breakpoint",
        "Slide-down panel with all nav links and CTA",
        "Include LocaleSwitcher inside mobile menu"
      ],
      "category": "ux",
      "impact": "high",
      "effort": "S",
      "risk": "low",
      "targetFiles": [
        "src/components/Header.tsx",
        "src/components/LocaleSwitcher.tsx"
      ],
      "id": "card-3",
      "status": "proposed"
    },
    {
      "track": "whats_next",
      "title": "Add competitor comparison pages for SEO",
      "rationale": "Chatbase and Tidio rank for 'MonGPT vs X' queries; MonGPT has no comparison pages.",
      "bullets": [
        "Create /compare/[slug]/ dynamic route",
        "Feature and price comparison table component",
        "Add comparison entries to sitemap.ts"
      ],
      "category": "growth",
      "impact": "high",
      "effort": "M",
      "risk": "low",
      "targetFiles": [
        "src/app/compare/[slug]/page.tsx",
        "src/components/CompareTable.tsx",
        "src/lib/dict/compare.ts",
        "src/app/sitemap.ts"
      ],
      "id": "card-4",
      "status": "proposed"
    },
    {
      "track": "whats_next",
      "title": "Add interactive widget customizer page",
      "rationale": "Let visitors preview and tweak widget styling before signup — visually demoable and converts.",
      "bullets": [
        "Color picker for brand and bubble colors",
        "Position and greeting text controls",
        "Live preview using DemoWidget with custom config"
      ],
      "category": "feature",
      "impact": "medium",
      "effort": "M",
      "risk": "low",
      "targetFiles": [
        "src/app/customize/page.tsx",
        "src/components/WidgetCustomizer.tsx",
        "src/components/DemoWidget.tsx"
      ],
      "id": "card-5",
      "status": "proposed"
    },
    {
      "track": "whats_next",
      "title": "Add customer testimonials and case studies page",
      "rationale": "No social proof exists anywhere on the site; competitors feature testimonials prominently.",
      "bullets": [
        "Testimonials grid with customer logos and quotes",
        "Case study cards with before/after metrics",
        "Add to Footer product column and sitemap"
      ],
      "category": "growth",
      "impact": "medium",
      "effort": "M",
      "risk": "low",
      "targetFiles": [
        "src/app/customers/page.tsx",
        "src/components/Testimonials.tsx",
        "src/components/Footer.tsx",
        "src/app/sitemap.ts"
      ],
      "id": "card-6",
      "status": "proposed"
    }
  ],
  "generatedAt": "2026-07-18T06:33:50.643Z"
}